local_env_setup/__init__.py
local_env_setup/config/__init__.py
local_env_setup/config/env.py
local_env_setup/core/__init__.py
local_env_setup/core/base.py
local_env_setup/core/logging.py
local_env_setup/core/monitoring.py
local_env_setup/scripts/__init__.py
local_env_setup/scripts/local_env_setup.py
local_env_setup/setup/__init__.py
local_env_setup/setup/dev_tools/git.py
local_env_setup/setup/dev_tools/python.py
local_env_setup/setup/infra/docker.py
local_env_setup/setup/infra/kubernetes.py
local_env_setup/setup/infra/terraform.py
local_env_setup/setup/os/homebrew.py
local_env_setup/setup/os/shell.py
local_env_setup/utils/__init__.py
local_env_setup/utils/env.py
local_env_setup/utils/file.py
local_env_setup/utils/shell.py
local_env_setup-0.1.0.dist-info/METADATA
local_env_setup-0.1.0.dist-info/WHEEL
local_env_setup-0.1.0.dist-info/entry_points.txt
local_env_setup-0.1.0.dist-info/RECORD
