Metadata-Version: 2.3
Name: local_env_setup
Version: 0.1.0
Summary: A command-line tool to automate the setup of a local development environment on macOS
License: MIT
Author: Your Name
Author-email: your.email@example.com
Requires-Python: >=3.9,<4.0
Classifier: Development Status :: 3 - Alpha
Classifier: Intended Audience :: Developers
Classifier: License :: OSI Approved :: MIT License
Classifier: Programming Language :: Python :: 3
Classifier: Programming Language :: Python :: 3.9
Classifier: Programming Language :: Python :: 3.10
Classifier: Programming Language :: Python :: 3.11
Classifier: Programming Language :: Python :: 3.12
Classifier: Programming Language :: Python :: 3.13
Requires-Dist: argparse (>=1.4.0,<2.0.0)
Requires-Dist: dotenv (>=0.9.9,<0.10.0)
Requires-Dist: python-dotenv (>=1.1.0,<2.0.0)
Requires-Dist: pyyaml (>=6.0,<7.0)
Requires-Dist: requests (>=2.28.0,<3.0.0)
Requires-Dist: rich (>=12.0.0,<13.0.0)
Project-URL: Repository, https://github.com/yourusername/local_env_setup
